LICENSE
MANIFEST.in
README.md
__init__.py
config.py
db.py
evaluate.py
eventloop.py
eventloop0.py
fileutils.py
iputils.py
lextab.py
log.py
oneconnect.py
parameters.py
parsetab.py
restutils.py
rpcweb.py
runcommand.py
setup.py
timeoutxmlrpccli.py
version.py
xmlobject.py
xmlrpcutils.py
./__init__.py
./config.py
./db.py
./evaluate.py
./eventloop.py
./eventloop0.py
./fileutils.py
./iputils.py
./lextab.py
./log.py
./oneconnect.py
./parameters.py
./parsetab.py
./restutils.py
./rpcweb.py
./runcommand.py
./timeoutxmlrpccli.py
./version.py
./xmlobject.py
./xmlrpcutils.py
cpyutils.egg-info/PKG-INFO
cpyutils.egg-info/SOURCES.txt
cpyutils.egg-info/dependency_links.txt
cpyutils.egg-info/top_level.txt