Metadata-Version: 1.0
Name: cpyutils
Version: 0.25
Summary: CLUES Python utils - Utils and General classes that spin off from CLUES
Home-page: https://github.com/grycap/cpyutils
Author: Carlos de Alfonso
Author-email: caralla@upv.es
License: UNKNOWN
Platform: UNKNOWN
